powerline_k8s/__init__.py
powerline_k8s/segments.py
powerline_k8s-1.5.4.dist-info/METADATA
powerline_k8s-1.5.4.dist-info/WHEEL
powerline_k8s-1.5.4.dist-info/licenses/LICENSE
powerline_k8s-1.5.4.dist-info/RECORD
