Metadata-Version: 2.4
Name: powerline-k8s
Version: 1.5.4
Summary: A custom Powerline segment for displaying the current Kubernetes context and namespace
Project-URL: Homepage, https://github.com/j4ckofalltrades/powerline-k8s
Project-URL: Repository, https://github.com/j4ckofalltrades/powerline-k8s
Project-URL: Documentation, https://j4ckofalltrades.github.io/powerline-k8s
Project-URL: Bug Tracker, https://github.com/j4ckofalltrades/powerline-k8s/issues
Author-email: Jordan Duabe <me@jduabe.dev>
License-Expression: MIT
License-File: LICENSE
Keywords: kubernetes,powerline
Classifier: Development Status :: 5 - Production/Stable
Classifier: Intended Audience :: Developers
Classifier: License :: OSI Approved :: MIT License
Classifier: Programming Language :: Python :: 3
Classifier: Programming Language :: Python :: 3.10
Classifier: Programming Language :: Python :: 3.11
Classifier: Programming Language :: Python :: 3.12
Requires-Python: >=3.10
Requires-Dist: kubernetes>=33.1.0
Requires-Dist: powerline-status>=2.7
Provides-Extra: docs
Requires-Dist: pdoc>=15.0.4; extra == 'docs'
Provides-Extra: test
Requires-Dist: pytest-cov>=6.2.1; extra == 'test'
Requires-Dist: pytest>=8.4.1; extra == 'test'
